ssh_backup/cli/main.py
ssh_backup/server/main.py
guiosoft_ssh_backup-0.1.0.dist-info/LICENSE
guiosoft_ssh_backup-0.1.0.dist-info/METADATA
guiosoft_ssh_backup-0.1.0.dist-info/WHEEL
guiosoft_ssh_backup-0.1.0.dist-info/RECORD
